OrgAlkCalc.py
SausageMachine.py
OrgAlkCalc-0.1.10.dist-info/LICENCE
OrgAlkCalc-0.1.10.dist-info/METADATA
OrgAlkCalc-0.1.10.dist-info/WHEEL
OrgAlkCalc-0.1.10.dist-info/top_level.txt
OrgAlkCalc-0.1.10.dist-info/RECORD
